CHANGELOG
LICENSE
MANIFEST.in
README.md
mnet.conf
mnet.py
setup.py
mnet.egg-info/PKG-INFO
mnet.egg-info/SOURCES.txt
mnet.egg-info/dependency_links.txt
mnet.egg-info/requires.txt
mnet.egg-info/top_level.txt
mnetsuite/__init__.py
mnetsuite/_version.py
mnetsuite/config.py
mnetsuite/network.py
mnetsuite/node.py
mnetsuite/node_stack.py
mnetsuite/node_vss.py
mnetsuite/output.py
mnetsuite/output_catalog.py
mnetsuite/output_diagram.py
mnetsuite/output_stdout.py
mnetsuite/snmp.py
mnetsuite/tracemac.py
mnetsuite/util.py