Metadata-Version: 1.1
Name: mnet
Version: 0.10
Summary: MNet Suite is a collection of Python tools for network professionals.
Home-page: http://github.com/MJL85/mnet/
Author: Michael Laforest
Author-email: mjlaforest@gmail.com
License: LICENSE
Keywords: python network cisco diagram snmp cdp
Platform: UNKNOWN
Classifier: Development Status :: 4 - Beta
Classifier: Intended Audience :: Information Technology
Classifier: License :: OSI Approved :: GNU General Public License v2 (GPLv2)
Classifier: Operating System :: OS Independent
Classifier: Programming Language :: Python
Classifier: Topic :: Utilities
